{
  "last_updated": "2026-06-28T14:05:50.633538",
  "news": [
    {
  "last_updated": "2026-06-29T13:48:40.632025",
  "news": [
    {
      "date": "2026-06-29",
      "source": "Instagram",
      "title": "Season 2026 Kickoff!",
      "content": "We are excited to start another winning year."
    },
    {
      "date": "2026-06-29",
      "source": "SRVA",
      "title": "Registration Info Updated",
      "content": "Check SRVAonline for latest club and player registration steps."
    },
    {
      "date": "2026-06-28",
      "source": "Facebook",
      "title": "Tryout Info Session Tonight",
      "content": "Join us on Zoom at 7 PM."
    },
    {
      "date": "2026-06-28",
      "source": "Instagram",
      "title": "New Practice Gear Arriving!",
      "content": "Check our stories for a sneak peek."
    },
    {
      "date": "2026-06-28",
      "source": "Website",
      "title": "Private Lesson",
      "content": "Latest update from our website."
    },
    {
      "date": "2026-06-28",
      "source": "Website",
      "title": "Open Programs",
      "content": "Latest update from our website."
    },
    {
      "date": "2026-06-28",
      "source": "Website",
      "title": "2025-2026 Club Tryouts",
      "content": "Latest update from our website."
    },
    {
      "date": "2026-06-28",
      "source": "USA Volleyball",
      "title": "Safety Guidelines Updated",
      "content": "New protocols for tournament medical staff."
    },
    {
      "date": "2026-06-28",
      "source": "USA Volleyball",
      "title": "2025 Rulebook Released",
      "content": "Minor changes to net touch interpretations."
    },
    {
      "date": "2026-06-28",
      "source": "Facebook",
      "title": "Summer Camp Registration Open",
      "content": "Sign up now for our July skills camp!"
    },
    {
      "date": "2025-11-01",
      "source": "Website",
      "title": "November Newsletter Released",
      "content": "Program guides and practice schedules for the 2025-2026 season are now available."
    },
    {
      "date": "2025-10-25",
      "source": "Instagram",
      "title": "Alumni Spotlight: Makenna Shotwell",
      "content": "Makenna Shotwell continues to shine at Merrimack with a career-high 20 kills!"
    }
  ],
  "rules": {
    "usav_summary": "USA Volleyball 2024-2025 rules include updates on uniform legality (Arabic numerals 1-99 required, contrasting colors for Libero) and allowing small, snug-fitting jewelry like nose rings and ear cuffs.",
    "srva_summary": "SRVA (Southern Region Volleyball Association) governs regional tournament registrations and club management. All players and staff must be registered via the SRVAonline system.",
    "expert_info": "USA Volleyball rules are the standard for our club. Key areas include service order, Libero transitions, and net contact rules. SRVA specific regulations often deal with tournament entry deadlines and roster requirements."
    "usav_summary": "USA Volleyball 2024-2025 rules: Jewelry is allowed if small and snug-fitting (nose rings/ear cuffs ok); Uniform numbers must be centered and clearly visible; Protests on judgment decisions are not allowed and may result in a penalty for the coach.",
    "srva_summary": "SRVA requires all athletes and staff to be registered via SRVAonline. Athletes must 'Accept' Mid TN VBC as their club in the SRVA system to be eligible for tournaments.",
    "expert_info": "We follow USA Volleyball and SRVA standards. Key areas: service order, Libero transitions, and tournament eligibility via SRVA membership."
  },
  "faqs": [
    {
      "q": "What is the cost of tryouts?",
      "a": "Tryouts cost $50 if you pre-register online, or $60 for walk-ups on the day of the event."
    },
    {
      "q": "Where do I sign in for tryouts?",
      "a": "Check-in and sign-in occur at our main facility located at 6910 Stroop Ln, Smyrna, TN 37167. Please arrive 30 minutes early."
    },
    {
      "q": "When will we know team placements?",
      "a": "Offers are typically sent out via email within 48-72 hours after the final tryout session for your age group."
    },
    {
      "q": "What do I need to be ready for?",
      "a": "Athletes should bring water, knee pads, and be ready for physical testing (height, reach, vertical) and agility drills (shuttle run) before moving into skill-based evaluations."
      "a": "Tryouts cost $50 for pre-registration and $60 for walk-ups."
    },
    {
      "q": "Where do I sign in for tryouts?",
      "a": "Sign-in is at our facility: 6910 Stroop Ln, Smyrna, TN 37167. Please arrive 30 mins early."
    },
    {
      "q": "What do I need to be ready for?",
      "a": "Be ready for physical testing (height, reach, vertical) and agility (shuttle run), followed by skill drills. Bring water and knee pads."
    }
  ]
}